edc_model_fields/__init__.py
edc_model_fields/apps.py
edc_model_fields/models.py
edc_model_fields/utils.py
edc_model_fields/fields/__init__.py
edc_model_fields/fields/custom_django_fields.py
edc_model_fields/fields/date_estimated.py
edc_model_fields/fields/hostname_modification_field.py
edc_model_fields/fields/identity_type_field.py
edc_model_fields/fields/initials_field.py
edc_model_fields/fields/other_charfield.py
edc_model_fields/fields/userfield.py
edc_model_fields/static/edc_model_fields/slider.css
edc_model_fields/static/edc_model_fields/slider.png
edc_model_fields/templates/edc_model_fields/widgets/slider.html
edc_model_fields/tests/__init__.py
edc_model_fields/tests/holidays.csv
edc_model_fields/tests/models.py
edc_model_fields/tests/test_settings.py
edc_model_fields/tests/urls.py
edc_model_fields/tests/etc/user-aes-local.key
edc_model_fields/tests/etc/user-aes-restricted.key
edc_model_fields/tests/etc/user-rsa-local-private.pem
edc_model_fields/tests/etc/user-rsa-local-public.pem
edc_model_fields/tests/etc/user-rsa-restricted-private.pem
edc_model_fields/tests/etc/user-rsa-restricted-public.pem
edc_model_fields/tests/etc/user-salt-local.key
edc_model_fields/tests/etc/user-salt-restricted.key
edc_model_fields/tests/tests/__init__.py
edc_model_fields/tests/tests/test_fields.py
edc_model_fields/widgets/__init__.py
edc_model_fields/widgets/slider_widget.py
edc_model_fields-1.0.0.dist-info/AUTHORS
edc_model_fields-1.0.0.dist-info/LICENSE
edc_model_fields-1.0.0.dist-info/METADATA
edc_model_fields-1.0.0.dist-info/WHEEL
edc_model_fields-1.0.0.dist-info/top_level.txt
edc_model_fields-1.0.0.dist-info/RECORD
